postleid/__init__.py
postleid/__main__.py
postleid/commandline.py
postleid/commons.py
postleid/fix_excel_files.py
postleid/paths.py
postleid/presets.py
postleid/py.typed
postleid/rule_checks.py
postleid/testdata.py
postleid/data/country_names_by_cc.yaml
postleid/data/default_user_settings.yaml
postleid/data/postal_code_rules_by_cc.yaml
postleid/locale/de/LC_MESSAGES/argparse.mo
postleid-0.8.1.dist-info/LICENSE
postleid-0.8.1.dist-info/METADATA
postleid-0.8.1.dist-info/WHEEL
postleid-0.8.1.dist-info/top_level.txt
postleid-0.8.1.dist-info/RECORD
