Metadata-Version: 2.1
Name: postleid
Version: 0.8.1
Summary: Postleid - sanitize postal codes in spreadsheads
Author-email: Rainer Schwarzbach <rainer@blackstream.de>
License: MIT License
Project-URL: Homepage, https://gitlab.com/blackstream-x/postleid
Project-URL: Documentation, https://blackstream-x.gitlab.io/postleid
Project-URL: CI, https://gitlab.com/blackstream-x/postleid/-/pipelines
Project-URL: Bug Tracker, https://gitlab.com/blackstream-x/postleid/-/issues
Project-URL: Repository, https://gitlab.com/blackstream-x/postleid.git
Keywords: postleitzahlen,plz,postal codes,excel
Classifier: Development Status :: 4 - Beta
Classifier: Environment :: Console
Classifier: Intended Audience :: End Users/Desktop
Classifier: License :: OSI Approved :: MIT License
Classifier: Natural Language :: German
Classifier: Operating System :: OS Independent
Classifier: Programming Language :: Python :: 3
Classifier: Programming Language :: Python :: 3.8
Classifier: Programming Language :: Python :: 3.9
Classifier: Programming Language :: Python :: 3.10
Classifier: Programming Language :: Python :: 3.11
Classifier: Programming Language :: Python :: 3.12
Classifier: Programming Language :: Python :: 3 :: Only
Classifier: Topic :: Office/Business
Classifier: Topic :: Utilities
Requires-Python: >=3.8
License-File: LICENSE
Requires-Dist: polars >=0.19.11
Requires-Dist: PyYAML >=6.0.1
Requires-Dist: qrstu >=0.2.0
Requires-Dist: xlsx2csv >=0.8.1
Requires-Dist: XlsxWriter >=3.1.9
